soft_comp/__init__.py
soft_comp/datasets.py
soft_comp/ea.py
soft_comp/fuzzy.py
soft_comp/notebook.py
soft_comp/perceptron.py
soft_comp/sigmoid_mlp.py
soft_comp/solver.py
soft_comp-0.0.1.dev25.dist-info/AUTHORS
soft_comp-0.0.1.dev25.dist-info/METADATA
soft_comp-0.0.1.dev25.dist-info/WHEEL
soft_comp-0.0.1.dev25.dist-info/pbr.json
soft_comp-0.0.1.dev25.dist-info/top_level.txt
soft_comp-0.0.1.dev25.dist-info/RECORD
